pyrefly-0.46.3.data/scripts/pyrefly
pyrefly-0.46.3.dist-info/METADATA
pyrefly-0.46.3.dist-info/WHEEL
pyrefly/__init__.py
pyrefly/__main__.py
pyrefly/py.typed
pyrefly-0.46.3.dist-info/RECORD
