Metadata-Version: 2.4
Name: pyrefly
Version: 0.46.3
Classifier: Development Status :: 4 - Beta
Classifier: Programming Language :: Python
Classifier: Programming Language :: Python :: 3
Classifier: Programming Language :: Python :: 3 :: Only
Classifier: Operating System :: MacOS
Classifier: Operating System :: Microsoft :: Windows
Classifier: Operating System :: POSIX :: Linux
Classifier: Intended Audience :: Developers
Classifier: Topic :: Software Development
Summary: A fast type checker and language server for Python with powerful IDE features
Keywords: typechecker,typechecking
Requires-Python: >=3.8
Project-URL: homepage, https://pyrefly.org
Project-URL: documentation, https://pyrefly.org/en/docs/
